BlackJackTable/__init__.py
BlackJackTable/main.py
BlackJackTable-0.2.7.dist-info/LICENSE
BlackJackTable-0.2.7.dist-info/METADATA
BlackJackTable-0.2.7.dist-info/WHEEL
BlackJackTable-0.2.7.dist-info/top_level.txt
BlackJackTable-0.2.7.dist-info/RECORD
