Metadata-Version: 2.1
Name: BlackJackTable
Version: 0.2.7
Author: zedMar65
License-File: LICENSE
